{"nodes": [{"id": "mias_client_src_lib_utils_forms_ts", "label": "forms.ts", "file_type": "code", "source_file": "mias-client/src/lib/utils/forms.ts", "source_location": "L1"}, {"id": "forms_iscaserecordlikeform", "label": "isCaseRecordLikeForm()", "file_type": "code", "source_file": "mias-client/src/lib/utils/forms.ts", "source_location": "L49"}, {"id": "forms_buildcaserecordproceduremap", "label": "buildCaseRecordProcedureMap()", "file_type": "code", "source_file": "mias-client/src/lib/utils/forms.ts", "source_location": "L61"}, {"id": "forms_mergeproceduremaps", "label": "mergeProcedureMaps()", "file_type": "code", "source_file": "mias-client/src/lib/utils/forms.ts", "source_location": "L79"}, {"id": "forms_resolvecaserecordfields", "label": "resolveCaseRecordFields()", "file_type": "code", "source_file": "mias-client/src/lib/utils/forms.ts", "source_location": "L102"}, {"id": "forms_stringifyformvalue", "label": "stringifyFormValue()", "file_type": "code", "source_file": "mias-client/src/lib/utils/forms.ts", "source_location": "L121"}, {"id": "forms_resolveformfieldsbytype", "label": "resolveFormFieldsByType()", "file_type": "code", "source_file": "mias-client/src/lib/utils/forms.ts", "source_location": "L143"}, {"id": "forms_mergefieldoptions", "label": "mergeFieldOptions()", "file_type": "code", "source_file": "mias-client/src/lib/utils/forms.ts", "source_location": "L155"}, {"id": "forms_isuploadedformfile", "label": "isUploadedFormFile()", "file_type": "code", "source_file": "mias-client/src/lib/utils/forms.ts", "source_location": "L168"}, {"id": "forms_asoptionalstring", "label": "asOptionalString()", "file_type": "code", "source_file": "mias-client/src/lib/utils/forms.ts", "source_location": "L172"}, {"id": "forms_asoptionalnumber", "label": "asOptionalNumber()", "file_type": "code", "source_file": "mias-client/src/lib/utils/forms.ts", "source_location": "L177"}, {"id": "forms_appendsupplementaltext", "label": "appendSupplementalText()", "file_type": "code", "source_file": "mias-client/src/lib/utils/forms.ts", "source_location": "L185"}, {"id": "forms_buildsupplementalformdescription", "label": "buildSupplementalFormDescription()", "file_type": "code", "source_file": "mias-client/src/lib/utils/forms.ts", "source_location": "L197"}, {"id": "forms_buildadmissionassessmentsubmission", "label": "buildAdmissionAssessmentSubmission()", "file_type": "code", "source_file": "mias-client/src/lib/utils/forms.ts", "source_location": "L215"}, {"id": "forms_persistformfiles", "label": "persistFormFiles()", "file_type": "code", "source_file": "mias-client/src/lib/utils/forms.ts", "source_location": "L255"}, {"id": "forms_buildcaserecorddescription", "label": "buildCaseRecordDescription()", "file_type": "code", "source_file": "mias-client/src/lib/utils/forms.ts", "source_location": "L294"}], "edges": [{"source": "mias_client_src_lib_utils_forms_ts", "target": "procedure_fields", "relation": "imports_from", "confidence": "EXTRACTED", "source_file": "mias-client/src/lib/utils/forms.ts", "source_location": "L1", "weight": 1.0}, {"source": "mias_client_src_lib_utils_forms_ts", "target": "forms", "relation": "imports_from", "confidence": "EXTRACTED", "source_file": "mias-client/src/lib/utils/forms.ts", "source_location": "L2", "weight": 1.0}, {"source": "mias_client_src_lib_utils_forms_ts", "target": "forms_iscaserecordlikeform", "relation": "contains", "confidence": "EXTRACTED", "source_file": "mias-client/src/lib/utils/forms.ts", "source_location": "L49", "weight": 1.0}, {"source": "mias_client_src_lib_utils_forms_ts", "target": "forms_buildcaserecordproceduremap", "relation": "contains", "confidence": "EXTRACTED", "source_file": "mias-client/src/lib/utils/forms.ts", "source_location": "L61", "weight": 1.0}, {"source": "mias_client_src_lib_utils_forms_ts", "target": "forms_mergeproceduremaps", "relation": "contains", "confidence": "EXTRACTED", "source_file": "mias-client/src/lib/utils/forms.ts", "source_location": "L79", "weight": 1.0}, {"source": "mias_client_src_lib_utils_forms_ts", "target": "forms_resolvecaserecordfields", "relation": "contains", "confidence": "EXTRACTED", "source_file": "mias-client/src/lib/utils/forms.ts", "source_location": "L102", "weight": 1.0}, {"source": "mias_client_src_lib_utils_forms_ts", "target": "forms_stringifyformvalue", "relation": "contains", "confidence": "EXTRACTED", "source_file": "mias-client/src/lib/utils/forms.ts", "source_location": "L121", "weight": 1.0}, {"source": "mias_client_src_lib_utils_forms_ts", "target": "forms_resolveformfieldsbytype", "relation": "contains", "confidence": "EXTRACTED", "source_file": "mias-client/src/lib/utils/forms.ts", "source_location": "L143", "weight": 1.0}, {"source": "mias_client_src_lib_utils_forms_ts", "target": "forms_mergefieldoptions", "relation": "contains", "confidence": "EXTRACTED", "source_file": "mias-client/src/lib/utils/forms.ts", "source_location": "L155", "weight": 1.0}, {"source": "mias_client_src_lib_utils_forms_ts", "target": "forms_isuploadedformfile", "relation": "contains", "confidence": "EXTRACTED", "source_file": "mias-client/src/lib/utils/forms.ts", "source_location": "L168", "weight": 1.0}, {"source": "mias_client_src_lib_utils_forms_ts", "target": "forms_asoptionalstring", "relation": "contains", "confidence": "EXTRACTED", "source_file": "mias-client/src/lib/utils/forms.ts", "source_location": "L172", "weight": 1.0}, {"source": "mias_client_src_lib_utils_forms_ts", "target": "forms_asoptionalnumber", "relation": "contains", "confidence": "EXTRACTED", "source_file": "mias-client/src/lib/utils/forms.ts", "source_location": "L177", "weight": 1.0}, {"source": "mias_client_src_lib_utils_forms_ts", "target": "forms_appendsupplementaltext", "relation": "contains", "confidence": "EXTRACTED", "source_file": "mias-client/src/lib/utils/forms.ts", "source_location": "L185", "weight": 1.0}, {"source": "mias_client_src_lib_utils_forms_ts", "target": "forms_buildsupplementalformdescription", "relation": "contains", "confidence": "EXTRACTED", "source_file": "mias-client/src/lib/utils/forms.ts", "source_location": "L197", "weight": 1.0}, {"source": "mias_client_src_lib_utils_forms_ts", "target": "forms_buildadmissionassessmentsubmission", "relation": "contains", "confidence": "EXTRACTED", "source_file": "mias-client/src/lib/utils/forms.ts", "source_location": "L215", "weight": 1.0}, {"source": "mias_client_src_lib_utils_forms_ts", "target": "forms_persistformfiles", "relation": "contains", "confidence": "EXTRACTED", "source_file": "mias-client/src/lib/utils/forms.ts", "source_location": "L255", "weight": 1.0}, {"source": "mias_client_src_lib_utils_forms_ts", "target": "forms_buildcaserecorddescription", "relation": "contains", "confidence": "EXTRACTED", "source_file": "mias-client/src/lib/utils/forms.ts", "source_location": "L294", "weight": 1.0}, {"source": "forms_buildcaserecordproceduremap", "target": "forms_iscaserecordlikeform", "relation": "calls", "confidence": "EXTRACTED", "source_file": "mias-client/src/lib/utils/forms.ts", "source_location": "L65", "weight": 1.0}, {"source": "forms_stringifyformvalue", "target": "forms_isuploadedformfile", "relation": "calls", "confidence": "EXTRACTED", "source_file": "mias-client/src/lib/utils/forms.ts", "source_location": "L134", "weight": 1.0}, {"source": "forms_asoptionalstring", "target": "forms_stringifyformvalue", "relation": "calls", "confidence": "EXTRACTED", "source_file": "mias-client/src/lib/utils/forms.ts", "source_location": "L173", "weight": 1.0}, {"source": "forms_buildsupplementalformdescription", "target": "forms_stringifyformvalue", "relation": "calls", "confidence": "EXTRACTED", "source_file": "mias-client/src/lib/utils/forms.ts", "source_location": "L207", "weight": 1.0}, {"source": "forms_buildadmissionassessmentsubmission", "target": "forms_asoptionalstring", "relation": "calls", "confidence": "EXTRACTED", "source_file": "mias-client/src/lib/utils/forms.ts", "source_location": "L220", "weight": 1.0}, {"source": "forms_buildadmissionassessmentsubmission", "target": "forms_asoptionalnumber", "relation": "calls", "confidence": "EXTRACTED", "source_file": "mias-client/src/lib/utils/forms.ts", "source_location": "L243", "weight": 1.0}, {"source": "forms_buildadmissionassessmentsubmission", "target": "forms_appendsupplementaltext", "relation": "calls", "confidence": "EXTRACTED", "source_file": "mias-client/src/lib/utils/forms.ts", "source_location": "L248", "weight": 1.0}, {"source": "forms_buildadmissionassessmentsubmission", "target": "forms_buildsupplementalformdescription", "relation": "calls", "confidence": "EXTRACTED", "source_file": "mias-client/src/lib/utils/forms.ts", "source_location": "L250", "weight": 1.0}, {"source": "forms_buildcaserecorddescription", "target": "forms_stringifyformvalue", "relation": "calls", "confidence": "EXTRACTED", "source_file": "mias-client/src/lib/utils/forms.ts", "source_location": "L307", "weight": 1.0}], "raw_calls": [{"caller_nid": "forms_iscaserecordlikeform", "callee": "toUpperCase", "source_file": "mias-client/src/lib/utils/forms.ts", "source_location": "L52"}, {"caller_nid": "forms_iscaserecordlikeform", "callee": "toUpperCase", "source_file": "mias-client/src/lib/utils/forms.ts", "source_location": "L53"}, {"caller_nid": "forms_iscaserecordlikeform", "callee": "Boolean", "source_file": "mias-client/src/lib/utils/forms.ts", "source_location": "L54"}, {"caller_nid": "forms_buildcaserecordproceduremap", "callee": "includes", "source_file": "mias-client/src/lib/utils/forms.ts", "source_location": "L71"}, {"caller_nid": "forms_buildcaserecordproceduremap", "callee": "push", "source_file": "mias-client/src/lib/utils/forms.ts", "source_location": "L72"}, {"caller_nid": "forms_mergeproceduremaps", "callee": "entries", "source_file": "mias-client/src/lib/utils/forms.ts", "source_location": "L84"}, {"caller_nid": "forms_mergeproceduremaps", "callee": "entries", "source_file": "mias-client/src/lib/utils/forms.ts", "source_location": "L88"}, {"caller_nid": "forms_mergeproceduremaps", "callee": "includes", "source_file": "mias-client/src/lib/utils/forms.ts", "source_location": "L93"}, {"caller_nid": "forms_mergeproceduremaps", "callee": "push", "source_file": "mias-client/src/lib/utils/forms.ts", "source_location": "L94"}, {"caller_nid": "forms_resolvecaserecordfields", "callee": "find", "source_file": "mias-client/src/lib/utils/forms.ts", "source_location": "L107"}, {"caller_nid": "forms_resolvecaserecordfields", "callee": "getProcedureFields", "source_file": "mias-client/src/lib/utils/forms.ts", "source_location": "L118"}, {"caller_nid": "forms_stringifyformvalue", "callee": "isArray", "source_file": "mias-client/src/lib/utils/forms.ts", "source_location": "L125"}, {"caller_nid": "forms_stringifyformvalue", "callee": "join", "source_file": "mias-client/src/lib/utils/forms.ts", "source_location": "L126"}, {"caller_nid": "forms_stringifyformvalue", "callee": "filter", "source_file": "mias-client/src/lib/utils/forms.ts", "source_location": "L126"}, {"caller_nid": "forms_stringifyformvalue", "callee": "map", "source_file": "mias-client/src/lib/utils/forms.ts", "source_location": "L126"}, {"caller_nid": "forms_stringifyformvalue", "callee": "join", "source_file": "mias-client/src/lib/utils/forms.ts", "source_location": "L132"}, {"caller_nid": "forms_stringifyformvalue", "callee": "map", "source_file": "mias-client/src/lib/utils/forms.ts", "source_location": "L132"}, {"caller_nid": "forms_stringifyformvalue", "callee": "from", "source_file": "mias-client/src/lib/utils/forms.ts", "source_location": "L132"}, {"caller_nid": "forms_stringifyformvalue", "callee": "stringify", "source_file": "mias-client/src/lib/utils/forms.ts", "source_location": "L138"}, {"caller_nid": "forms_stringifyformvalue", "callee": "String", "source_file": "mias-client/src/lib/utils/forms.ts", "source_location": "L140"}, {"caller_nid": "forms_resolveformfieldsbytype", "callee": "find", "source_file": "mias-client/src/lib/utils/forms.ts", "source_location": "L148"}, {"caller_nid": "forms_mergefieldoptions", "callee": "map", "source_file": "mias-client/src/lib/utils/forms.ts", "source_location": "L159"}, {"caller_nid": "forms_isuploadedformfile", "callee": "Boolean", "source_file": "mias-client/src/lib/utils/forms.ts", "source_location": "L169"}, {"caller_nid": "forms_asoptionalstring", "callee": "trim", "source_file": "mias-client/src/lib/utils/forms.ts", "source_location": "L173"}, {"caller_nid": "forms_asoptionalnumber", "callee": "Number", "source_file": "mias-client/src/lib/utils/forms.ts", "source_location": "L181"}, {"caller_nid": "forms_asoptionalnumber", "callee": "isFinite", "source_file": "mias-client/src/lib/utils/forms.ts", "source_location": "L182"}, {"caller_nid": "forms_appendsupplementaltext", "callee": "trim", "source_file": "mias-client/src/lib/utils/forms.ts", "source_location": "L186"}, {"caller_nid": "forms_appendsupplementaltext", "callee": "trim", "source_file": "mias-client/src/lib/utils/forms.ts", "source_location": "L187"}, {"caller_nid": "forms_buildsupplementalformdescription", "callee": "has", "source_file": "mias-client/src/lib/utils/forms.ts", "source_location": "L204"}, {"caller_nid": "forms_buildsupplementalformdescription", "callee": "push", "source_file": "mias-client/src/lib/utils/forms.ts", "source_location": "L209"}, {"caller_nid": "forms_buildsupplementalformdescription", "callee": "join", "source_file": "mias-client/src/lib/utils/forms.ts", "source_location": "L212"}, {"caller_nid": "forms_buildadmissionassessmentsubmission", "callee": "join", "source_file": "mias-client/src/lib/utils/forms.ts", "source_location": "L219"}, {"caller_nid": "forms_buildadmissionassessmentsubmission", "callee": "map", "source_file": "mias-client/src/lib/utils/forms.ts", "source_location": "L219"}, {"caller_nid": "forms_buildadmissionassessmentsubmission", "callee": "filter", "source_file": "mias-client/src/lib/utils/forms.ts", "source_location": "L219"}, {"caller_nid": "forms_persistformfiles", "callee": "isArray", "source_file": "mias-client/src/lib/utils/forms.ts", "source_location": "L273"}, {"caller_nid": "forms_persistformfiles", "callee": "push", "source_file": "mias-client/src/lib/utils/forms.ts", "source_location": "L277"}, {"caller_nid": "forms_persistformfiles", "callee": "uploadFile", "source_file": "mias-client/src/lib/utils/forms.ts", "source_location": "L277"}, {"caller_nid": "forms_persistformfiles", "callee": "push", "source_file": "mias-client/src/lib/utils/forms.ts", "source_location": "L279"}, {"caller_nid": "forms_persistformfiles", "callee": "uploadFile", "source_file": "mias-client/src/lib/utils/forms.ts", "source_location": "L287"}, {"caller_nid": "forms_buildcaserecorddescription", "callee": "has", "source_file": "mias-client/src/lib/utils/forms.ts", "source_location": "L304"}, {"caller_nid": "forms_buildcaserecorddescription", "callee": "push", "source_file": "mias-client/src/lib/utils/forms.ts", "source_location": "L309"}, {"caller_nid": "forms_buildcaserecorddescription", "callee": "join", "source_file": "mias-client/src/lib/utils/forms.ts", "source_location": "L313"}]}